{"id": "_7ee7fa9b", "title": "뱃노래2001", "youtube": [{"title": "Marine Song 2001 (ACNH)", "link": "https://www.youtube.com/watch?v=sEKH9bDnWtk"}, {"title": "Villagers Singing Marine Song 2001 Together - Animal Crossing: New Horizons", "link": "https://www.youtube.com/watch?v=45QJdw4Ezsw"}, {"title": "303 - Marine Song 2001 (Aircheck)", "link": "https://www.youtube.com/watch?v=6LFAfRMOTBM"}, {"title": "K.K. Slider - Marine Song 2001 - Animal Crossing City Folk", "link": "https://www.youtube.com/watch?v=UKy-KVwIChY"}, {"title": "Animal Crossing - Marine Song 2001 - English Cover", "link": "https://www.youtube.com/watch?v=GmdYxVNvo4s"}]}